psaw/PushshiftAPI.py
psaw/__init__.py
psaw/psaw.py
psaw/utilities.py
psaw/writers.py
psaw-0.0.11.dist-info/LICENSE
psaw-0.0.11.dist-info/METADATA
psaw-0.0.11.dist-info/WHEEL
psaw-0.0.11.dist-info/entry_points.txt
psaw-0.0.11.dist-info/top_level.txt
psaw-0.0.11.dist-info/RECORD
