Metadata-Version: 2.1
Name: psaw
Version: 0.0.11
Summary: Pushshift.io API Wrapper for reddit.com public comment/submission search
Home-page: http://github.com/dmarx/psaw
Author: David Marx
Author-email: david.marx84@gmail.com
License: Simplified BSD License
Keywords: reddit api wrapper pushshift
Platform: UNKNOWN
Classifier: Development Status :: 3 - Alpha
Classifier: Environment :: Console
Classifier: Intended Audience :: Developers
Classifier: License :: OSI Approved :: BSD License
Classifier: Natural Language :: English
Classifier: Operating System :: OS Independent
Classifier: Programming Language :: Python
Classifier: Programming Language :: Python :: 3
Classifier: Programming Language :: Python :: 3.4
Classifier: Programming Language :: Python :: 3.5
Classifier: Programming Language :: Python :: 3.6
Classifier: Programming Language :: Python :: 3 :: Only
Classifier: Programming Language :: Python :: Implementation :: CPython
Classifier: Topic :: Utilities
Requires-Python: >=3
Requires-Dist: requests
Requires-Dist: Click
